README.md
setup.py
pns/__init__.py
pns.egg-info/PKG-INFO
pns.egg-info/SOURCES.txt
pns.egg-info/dependency_links.txt
pns.egg-info/top_level.txt