Metadata-Version: 2.1
Name: pns
Version: 0.0.0
Summary: Resolver for port names
Home-page: https://github.com/deadbeef-development/pns
Author: Deadbeef-Development
Author-email: deadbeef.development@gmail.com
License: UNKNOWN
Platform: UNKNOWN
